{
	"Points": [
		{
			"X": 0,
			"Y": 0,
			"angle": 0,
			"type": "SetXYTheta"
		}, {
			"X": 220,
			"Y": 720,
			"type": "MoveToPosition"
		}, {
			"time": 500,
			"type": "Wait"
		}, {
			"angle": 135,
			"type": "AbsoluteAngle",
			"action": "openLeftClamp"
		}, {
			"X": 200,
			"Y": 0,
			"max_speed": 30,
			"timeout": 2000,
			"type": "MoveToPositionRelativeToAngle"
		}, {
			"action": "closeLeftClamp",
			"type": "Action"
		}, {
			"time": 500,
			"type": "Wait"
		}, {
			"action": "elevatorUp",
			"type": "Action"
		}, {
			"time": 500,
			"type": "Wait"
		} 
	]
}