{
	"Points": [
		{
			"time": 0,
			"type": "Wait"
		}, {
			"X": -200,
			"Y": -100,
			"type": "MoveToPositionRelativeToAngle",
			"direction": "backward",
			"max_speed": 50
		}, {
			"angle": -270,
			"type": "AbsoluteAngle"
		}, {
			"X": 30,
			"Y": 600,
			"type": "MoveToPosition"
		}, {
			"angle": -270,
			"type": "AbsoluteAngle"
		}, {
			"X": 400,
			"Y": 0,
			"type": "MoveToPositionRelativeToAngle",
			"timeout": 2000,
			"max_speed": 40
		}, {
			"action": "dropStatuette",
			"type": "Action"
		}, {
			"time": 1000,
			"type": "Wait"
		}
	]
}